{"models":[{"name":"class_addOrEdit","appName":"","modelName":"class_addOrEdit","url":"/jcsj-apps-web/class/addOrEdit","controls":[{"name":"wid","dataType":"string","caption":"班级wid","hidden":true},{"name":"gradeWid","dataType":"string","caption":"年级wid","hidden":true},{"name":"gradeName","dataType":"string","caption":"年级","required":true,"xtype":"select","placeholder":"请选择","url":"/jcsj-apps-web/code/getGrade"},{"name":"departWid","dataType":"string","caption":"院系wid","hidden":true},{"name":"departName","dataType":"string","caption":"院系","required":true,"xtype":"select","placeholder":"请选择","url":"/jcsj-apps-web/code/getDept"},{"name":"majorWid","dataType":"string","caption":"专业wid"},{"name":"majorName","dataType":"string","caption":"专业","required":true,"xtype":"select","placeholder":"请选择","url":"/jcsj-apps-web/code/getMajor"},{"name":"code","dataType":"integer","caption":"代码","required":true},{"name":"name","dataType":"string","caption":"名称","required":true},{"name":"shortName","dataType":"integer","caption":"简称","required":true},{"name":"expectedNumber","dataType":"integer","caption":"预计人数","required":true},{"name":"actualNumber","dataType":"integer","caption":"实际人数","required":true},{"name":"classRoomWid","dataType":"string","caption":"对应教室wid","hidden":true},{"name":"classRoom","dataType":"string","caption":"对应教室","xtype":"select","placeholder":"请选择","url":"/jcsj-apps-web/code/getClassRoom"},{"name":"status","dataType":"boolean","caption":"启用状态","xtype":"switcher"}]}]}