{"models":[{"name":"teachGroup_getByWid","appName":"","modelName":"teachGroup_getByWid","url":"/jcsj-apps-web/teachGroup/getByWid","controls":[{"name":"wid","dataType":"string","caption":"教研组wid","hidden":true},{"name":"code","dataType":"integer","caption":"代码","required":true},{"name":"name","dataType":"string","caption":"名称","required":true},{"name":"departWid","dataType":"string","caption":"所属单位wid","hidden":true},{"name":"depart","dataType":"string","caption":"所属单位","required":true,"xtype":"select","placeholder":"请选择","url":"/code/getDept"},{"name":"itemSort","dataType":"integer","caption":"排序","required":true},{"name":"status","dataType":"boolean","caption":"是否启用","xtype":"switcher"},{"name":"remark","dataType":"string","caption":"备注","xtype":"textarea"}]}]}